trackinglog/__init__.py
trackinglog/email_manager/__init__.py
trackinglog/email_manager/email_manager.py
trackinglog/log_manager/__init__.py
trackinglog/log_manager/log_manager.py
trackinglog/log_manager/log_manager_legacy.py
trackinglog/parameter_config/__init__.py
trackinglog/parameter_config/parameter_config.py
trackinglog/task_manager/__init__.py
trackinglog/task_manager/task_manager.py
trackinglog-0.2.0.2.dist-info/METADATA
trackinglog-0.2.0.2.dist-info/WHEEL
trackinglog-0.2.0.2.dist-info/top_level.txt
trackinglog-0.2.0.2.dist-info/RECORD
