Metadata-Version: 2.4
Name: trackinglog
Version: 0.2.0.2
Summary: A logging package for tracing function calls with error handling and email notification
Home-page: https://github.com/shiyi-yinghao/trackinglog
Author: Yinghao Li
Author-email: shiyi.yinghao@gmail.com
Requires-Python: >=3.9
Requires-Dist: numpy>=2.0.1
Requires-Dist: pandas>=2.2.2
Requires-Dist: line_profiler>=4.1.3
Dynamic: author
Dynamic: author-email
Dynamic: description
Dynamic: description-content-type
Dynamic: home-page
Dynamic: requires-dist
Dynamic: requires-python
Dynamic: summary
